LICENSE
README.md
setup.py
ctscams/__init__.py
ctscams/continous_time_series_cluster.py
ctscams/fine_tuning.py
ctscams/merging.py
ctscams.egg-info/PKG-INFO
ctscams.egg-info/SOURCES.txt
ctscams.egg-info/dependency_links.txt
ctscams.egg-info/requires.txt
ctscams.egg-info/top_level.txt