Metadata-Version: 2.1
Name: ctscams
Version: 0.0.1
Summary: Continous Time-Series Clustering And Merging towards Sentiments (CT-SCAMS) is a Python package ddesigned to ensure robust generalization across time stamps for sentiment analysis in policy-related texts. 
Author: Charles Alba
Author-email: alba@wustl.edu
Keywords: sentiment analysis,temporal,policy text,online text
Classifier: Development Status :: 1 - Planning
Classifier: Intended Audience :: Education
Classifier: Intended Audience :: Science/Research
Classifier: Programming Language :: Python :: 3
Classifier: Operating System :: Unix
Classifier: Operating System :: MacOS :: MacOS X
Classifier: Operating System :: Microsoft :: Windows
License-File: LICENSE
